odoo/addons/ssi_hr_employee_experience_from_work_address/README.rst
odoo/addons/ssi_hr_employee_experience_from_work_address/__init__.py
odoo/addons/ssi_hr_employee_experience_from_work_address/__manifest__.py
odoo/addons/ssi_hr_employee_experience_from_work_address/models/__init__.py
odoo/addons/ssi_hr_employee_experience_from_work_address/models/hr_employee.py
odoo/addons/ssi_hr_employee_experience_from_work_address/static/description/icon.png
odoo/addons/ssi_hr_employee_experience_from_work_address/views/hr_employee_views.xml
odoo14_addon_ssi_hr_employee_experience_from_work_address-14.0.1.2.0.dist-info/METADATA
odoo14_addon_ssi_hr_employee_experience_from_work_address-14.0.1.2.0.dist-info/WHEEL
odoo14_addon_ssi_hr_employee_experience_from_work_address-14.0.1.2.0.dist-info/top_level.txt
odoo14_addon_ssi_hr_employee_experience_from_work_address-14.0.1.2.0.dist-info/RECORD
